{
  "template_name": "Testtest",
  "version": "1.0",
  "created_date": "2025-08-19T23:30:32.512609",
  "description": "Mall sparad till fil: Testtest.json",
  "field_config": {
    "custom_names": {
      "obs": "Obs",
      "person_sak": "Tänk_på!",
      "special": "FUP",
      "ovrigt": "Viktigt",
      "note1": "Notering"
    },
    "disabled_fields": [
      "note3",
      "kalla3",
      "kalla2",
      "note2",
      "kategori",
      "underkategori"
    ],
    "hidden_fields": [
      "note3",
      "kalla3",
      "kalla2",
      "note2",
      "kategori",
      "underkategori"
    ]
  }
}